framed/__init__.py
framed/api.py
framed/cli.py
framed/config.py
framed/extractor.py
framed/processor.py
framed/runner.py
framed/simctl.py
framed/templates/__init__.py
framed/templates/_raw_samples/ja/Launch Screen.png
framed/templates/_raw_samples/ja/home_empty.png
framed/templates/_raw_samples/ja/inbox.png
framed/templates/_raw_samples/ja/onboarding.png
framed/templates/_raw_samples/ja/recording.png
framed/templates/panoramic/__init__.py
framed/templates/panoramic/template.yaml
framed/templates/panoramic/samples/01_onboarding.png
framed/templates/panoramic/samples/02_home_empty.png
framed/templates/panoramic/samples/03_recording.png
framed/templates/panoramic/samples/04_inbox.png
framed/templates/panoramic/samples/framed.yaml
framed/templates/standard/__init__.py
framed/templates/standard/template.yaml
framed/templates/standard/samples/01_onboarding.png
framed/templates/standard/samples/02_home_empty.png
framed/templates/standard/samples/03_recording.png
framed/templates/standard/samples/04_inbox.png
framed/templates/standard/samples/framed.yaml
framed_cli-0.1.0.dist-info/licenses/LICENSE
framed_cli-0.1.0.dist-info/METADATA
framed_cli-0.1.0.dist-info/WHEEL
framed_cli-0.1.0.dist-info/entry_points.txt
framed_cli-0.1.0.dist-info/top_level.txt
framed_cli-0.1.0.dist-info/RECORD
