Metadata-Version: 2.4
Name: framed-cli
Version: 0.1.0
Summary: Automated App Store screenshot generator for iOS
Author-email: yamshta <shymst125@gmail.com>
License: MIT License
Project-URL: Homepage, https://github.com/yamshta/framed
Classifier: Development Status :: 3 - Alpha
Classifier: Intended Audience :: Developers
Classifier: Topic :: Software Development :: Build Tools
Classifier: Programming Language :: Python :: 3
Classifier: Programming Language :: Python :: 3.10
Classifier: Programming Language :: Python :: 3.11
Classifier: License :: OSI Approved :: MIT License
Classifier: Operating System :: MacOS :: MacOS X
Requires-Python: >=3.10
License-File: LICENSE
Requires-Dist: click>=8.0
Requires-Dist: Pillow>=9.0
Requires-Dist: PyYAML>=6.0
Requires-Dist: numpy>=1.20
Dynamic: license-file
